{
    "2000": {
        "Resident Population (Person)": {
            "value": "47,732,558",
            "category_en": "Population",
            "category_kr": "인구"
        },
        "Births (Person)": {
            "value": "640,089",
            "category_en": "Population",
            "category_kr": "인구"
        },
        "Deaths (Person)": {
            "value": "248,740",
            "category_en": "Population",
            "category_kr": "인구"
        },
        "Resident Households (households)": {
            "value": "15,765,275",
            "category_en": "Population",
            "category_kr": "인구"
        },
        "GDP (Hund.M U$)": {
            "value": "5,976.7",
            "category_en": "Economy",
            "category_kr": "경제"
        },
        "mortality rate (per 100 thousand person)": {
            "value": "248,740",
            "category_en": "Health",
            "category_kr": "보건"
        },
        "Unemployment rate (%)": {
            "value": "4.4",
            "category_en": "Labor",
            "category_kr": "노동"
        }
    },
    "2001": {
        "Resident Population (Person)": {
            "value": "48,021,543",
            "category_en": "Population",
            "category_kr": "인구"
        },
        "Births (Person)": {
            "value": "559,934",
            "category_en": "Population",
            "category_kr": "인구"
        },
        "Deaths (Person)": {
            "value": "243,813",
            "category_en": "Population",
            "category_kr": "인구"
        },
        "Resident Households (households)": {
            "value": "16,080,992",
            "category_en": "Population",
            "category_kr": "인구"
        },
        "GDP (Hund.M U$)": {
            "value": "5,676.4",
            "category_en": "Economy",
            "category_kr": "경제"
        },
        "mortality rate (per 100 thousand person)": {
            "value": "243,813",
            "category_en": "Health",
            "category_kr": "보건"
        },
        "Unemployment rate (%)": {
            "value": "4.0",
            "category_en": "Labor",
            "category_kr": "노동"
        }
    },
    "2002": {
        "Resident Population (Person)": {
            "value": "48,229,948",
            "category_en": "Population",
            "category_kr": "인구"
        },
        "Births (Person)": {
            "value": "496,911",
            "category_en": "Population",
            "category_kr": "인구"
        },
        "Deaths (Person)": {
            "value": "247,524",
            "category_en": "Population",
            "category_kr": "인구"
        },
        "Resident Households (households)": {
            "value": "16,489,107",
            "category_en": "Population",
            "category_kr": "인구"
        },
        "GDP (Hund.M U$)": {
            "value": "6,499.4",
            "category_en": "Economy",
            "category_kr": "경제"
        },
        "mortality rate (per 100 thousand person)": {
            "value": "247,524",
            "category_en": "Health",
            "category_kr": "보건"
        },
        "Unemployment rate (%)": {
            "value": "3.3",
            "category_en": "Labor",
            "category_kr": "노동"
        }
    },
    "2003": {
        "Resident Population (Person)": {
            "value": "48,386,823",
            "category_en": "Population",
            "category_kr": "인구"
        },
        "Births (Person)": {
            "value": "495,036",
            "category_en": "Population",
            "category_kr": "인구"
        },
        "Deaths (Person)": {
            "value": "246,463",
            "category_en": "Population",
            "category_kr": "인구"
        },
        "Resident Households (households)": {
            "value": "16,987,634",
            "category_en": "Population",
            "category_kr": "인구"
        },
        "GDP (Hund.M U$)": {
            "value": "7,283.5",
            "category_en": "Economy",
            "category_kr": "경제"
        },
        "mortality rate (per 100 thousand person)": {
            "value": "246,463",
            "category_en": "Health",
            "category_kr": "보건"
        },
        "Unemployment rate (%)": {
            "value": "3.6",
            "category_en": "Labor",
            "category_kr": "노동"
        }
    },
    "2004": {
        "Resident Population (Person)": {
            "value": "48,583,805",
            "category_en": "Population",
            "category_kr": "인구"
        },
        "Births (Person)": {
            "value": "476,958",
            "category_en": "Population",
            "category_kr": "인구"
        },
        "Deaths (Person)": {
            "value": "246,220",
            "category_en": "Population",
            "category_kr": "인구"
        },
        "Resident Households (households)": {
            "value": "17,391,932",
            "category_en": "Population",
            "category_kr": "인구"
        },
        "GDP (Hund.M U$)": {
            "value": "8,237.2",
            "category_en": "Economy",
            "category_kr": "경제"
        },
        "mortality rate (per 100 thousand person)": {
            "value": "246,220",
            "category_en": "Health",
            "category_kr": "보건"
        },
        "Unemployment rate (%)": {
            "value": "3.7",
            "category_en": "Labor",
            "category_kr": "노동"
        }
    },
    "2005": {
        "Resident Population (Person)": {
            "value": "48,782,274",
            "category_en": "Population",
            "category_kr": "인구"
        },
        "Births (Person)": {
            "value": "438,707",
            "category_en": "Population",
            "category_kr": "인구"
        },
        "Deaths (Person)": {
            "value": "245,874",
            "category_en": "Population",
            "category_kr": "인구"
        },
        "Resident Households (households)": {
            "value": "17,857,511",
            "category_en": "Population",
            "category_kr": "인구"
        },
        "GDP (Hund.M U$)": {
            "value": "9,715.6",
            "category_en": "Economy",
            "category_kr": "경제"
        },
        "mortality rate (per 100 thousand person)": {
            "value": "245,874",
            "category_en": "Health",
            "category_kr": "보건"
        },
        "Unemployment rate (%)": {
            "value": "3.7",
            "category_en": "Labor",
            "category_kr": "노동"
        }
    },
    "2006": {
        "Resident Population (Person)": {
            "value": "48,991,779",
            "category_en": "Population",
            "category_kr": "인구"
        },
        "Births (Person)": {
            "value": "451,759",
            "category_en": "Population",
            "category_kr": "인구"
        },
        "Deaths (Person)": {
            "value": "244,162",
            "category_en": "Population",
            "category_kr": "인구"
        },
        "Resident Households (households)": {
            "value": "18,326,619",
            "category_en": "Population",
            "category_kr": "인구"
        },
        "GDP (Hund.M U$)": {
            "value": "10,943.5",
            "category_en": "Economy",
            "category_kr": "경제"
        },
        "mortality rate (per 100 thousand person)": {
            "value": "244,162",
            "category_en": "Health",
            "category_kr": "보건"
        },
        "Unemployment rate (%)": {
            "value": "3.5",
            "category_en": "Labor",
            "category_kr": "노동"
        }
    },
    "2007": {
        "Resident Population (Person)": {
            "value": "49,268,928",
            "category_en": "Population",
            "category_kr": "인구"
        },
        "Births (Person)": {
            "value": "496,822",
            "category_en": "Population",
            "category_kr": "인구"
        },
        "Deaths (Person)": {
            "value": "246,482",
            "category_en": "Population",
            "category_kr": "인구"
        },
        "Resident Households (households)": {
            "value": "18,687,694",
            "category_en": "Population",
            "category_kr": "인구"
        },
        "GDP (Hund.M U$)": {
            "value": "12,209.9",
            "category_en": "Economy",
            "category_kr": "경제"
        },
        "mortality rate (per 100 thousand person)": {
            "value": "246,482",
            "category_en": "Health",
            "category_kr": "보건"
        },
        "Unemployment rate (%)": {
            "value": "3.2",
            "category_en": "Labor",
            "category_kr": "노동"
        }
    },
    "2008": {
        "Resident Population (Person)": {
            "value": "49,540,367",
            "category_en": "Population",
            "category_kr": "인구"
        },
        "Births (Person)": {
            "value": "465,892",
            "category_en": "Population",
            "category_kr": "인구"
        },
        "Deaths (Person)": {
            "value": "246,113",
            "category_en": "Population",
            "category_kr": "인구"
        },
        "Resident Households (households)": {
            "value": "19,005,339",
            "category_en": "Population",
            "category_kr": "인구"
        },
        "GDP (Hund.M U$)": {
            "value": "10,910.4",
            "category_en": "Economy",
            "category_kr": "경제"
        },
        "mortality rate (per 100 thousand person)": {
            "value": "246,113",
            "category_en": "Health",
            "category_kr": "보건"
        },
        "Unemployment rate (%)": {
            "value": "3.2",
            "category_en": "Labor",
            "category_kr": "노동"
        }
    },
    "2009": {
        "Resident Population (Person)": {
            "value": "49,773,145",
            "category_en": "Population",
            "category_kr": "인구"
        },
        "Births (Person)": {
            "value": "444,849",
            "category_en": "Population",
            "category_kr": "인구"
        },
        "Deaths (Person)": {
            "value": "246,942",
            "category_en": "Population",
            "category_kr": "인구"
        },
        "Resident Households (households)": {
            "value": "19,261,292",
            "category_en": "Population",
            "category_kr": "인구"
        },
        "Registered Foreigners (Person)": {
            "value": "870,636",
            "category_en": "Population",
            "category_kr": "인구"
        },
        "GDP (Hund.M U$)": {
            "value": "9,834.7",
            "category_en": "Economy",
            "category_kr": "경제"
        },
        "mortality rate (per 100 thousand person)": {
            "value": "246,942",
            "category_en": "Health",
            "category_kr": "보건"
        },
        "Unemployment rate (%)": {
            "value": "3.6",
            "category_en": "Labor",
            "category_kr": "노동"
        },
        "Area of the land (㎡)": {
            "value": "99,897,411,054.6",
            "category_en": "Land Use",
            "category_kr": "국토이용"
        }
    },
    "2010": {
        "Resident Population (Person)": {
            "value": "50,515,666",
            "category_en": "Population",
            "category_kr": "인구"
        },
        "Births (Person)": {
            "value": "470,171",
            "category_en": "Population",
            "category_kr": "인구"
        },
        "Deaths (Person)": {
            "value": "255,405",
            "category_en": "Population",
            "category_kr": "인구"
        },
        "Resident Households (households)": {
            "value": "19,865,179",
            "category_en": "Population",
            "category_kr": "인구"
        },
        "Registered Foreigners (Person)": {
            "value": "918,917",
            "category_en": "Population",
            "category_kr": "인구"
        },
        "GDP (Hund.M U$)": {
            "value": "11,930.4",
            "category_en": "Economy",
            "category_kr": "경제"
        },
        "mortality rate (per 100 thousand person)": {
            "value": "255,405",
            "category_en": "Health",
            "category_kr": "보건"
        },
        "Unemployment rate (%)": {
            "value": "3.7",
            "category_en": "Labor",
            "category_kr": "노동"
        },
        "Liabilities (10 thousand won)": {
            "value": "4,618.33",
            "category_en": "Income, Consumption and Assets",
            "category_kr": "소득, 소비, 자산"
        },
        "Area of the land (㎡)": {
            "value": "100,033,075,827.1",
            "category_en": "Land Use",
            "category_kr": "국토이용"
        }
    },
    "2011": {
        "Resident Population (Person)": {
            "value": "50,734,284",
            "category_en": "Population",
            "category_kr": "인구"
        },
        "Births (Person)": {
            "value": "471,265",
            "category_en": "Population",
            "category_kr": "인구"
        },
        "Deaths (Person)": {
            "value": "257,396",
            "category_en": "Population",
            "category_kr": "인구"
        },
        "Resident Households (households)": {
            "value": "20,033,142",
            "category_en": "Population",
            "category_kr": "인구"
        },
        "Crime Occurrence (Cases)": {
            "value": "1,752,598",
            "category_en": "Crime & Safety",
            "category_kr": "범죄와 안전"
        },
        "Registered Foreigners (Person)": {
            "value": "982,461",
            "category_en": "Population",
            "category_kr": "인구"
        },
        "GDP (Hund.M U$)": {
            "value": "13,072.5",
            "category_en": "Economy",
            "category_kr": "경제"
        },
        "mortality rate (per 100 thousand person)": {
            "value": "257,396",
            "category_en": "Health",
            "category_kr": "보건"
        },
        "Unemployment rate (%)": {
            "value": "3.4",
            "category_en": "Labor",
            "category_kr": "노동"
        },
        "Liabilities (10 thousand won)": {
            "value": "5,204.79",
            "category_en": "Income, Consumption and Assets",
            "category_kr": "소득, 소비, 자산"
        },
        "Area of the land (㎡)": {
            "value": "100,148,218,044.1",
            "category_en": "Land Use",
            "category_kr": "국토이용"
        }
    },
    "2012": {
        "Resident Population (Person)": {
            "value": "50,948,272",
            "category_en": "Population",
            "category_kr": "인구"
        },
        "Births (Person)": {
            "value": "484,550",
            "category_en": "Population",
            "category_kr": "인구"
        },
        "Deaths (Person)": {
            "value": "267,221",
            "category_en": "Population",
            "category_kr": "인구"
        },
        "Resident Households (households)": {
            "value": "20,211,770",
            "category_en": "Population",
            "category_kr": "인구"
        },
        "Crime Occurrence (Cases)": {
            "value": "1,793,400",
            "category_en": "Crime & Safety",
            "category_kr": "범죄와 안전"
        },
        "Registered Foreigners (Person)": {
            "value": "932,983",
            "category_en": "Population",
            "category_kr": "인구"
        },
        "GDP (Hund.M U$)": {
            "value": "13,352.6",
            "category_en": "Economy",
            "category_kr": "경제"
        },
        "mortality rate (per 100 thousand person)": {
            "value": "267,221",
            "category_en": "Health",
            "category_kr": "보건"
        },
        "Unemployment rate (%)": {
            "value": "3.2",
            "category_en": "Labor",
            "category_kr": "노동"
        },
        "Liabilities (10 thousand won)": {
            "value": "5,449.60",
            "category_en": "Income, Consumption and Assets",
            "category_kr": "소득, 소비, 자산"
        },
        "Area of the land (㎡)": {
            "value": "100,188,083,290.4",
            "category_en": "Land Use",
            "category_kr": "국토이용"
        }
    },
    "2013": {
        "Resident Population (Person)": {
            "value": "51,141,463",
            "category_en": "Population",
            "category_kr": "인구"
        },
        "Births (Person)": {
            "value": "436,455",
            "category_en": "Population",
            "category_kr": "인구"
        },
        "Deaths (Person)": {
            "value": "266,257",
            "category_en": "Population",
            "category_kr": "인구"
        },
        "Resident Households (households)": {
            "value": "20,456,588",
            "category_en": "Population",
            "category_kr": "인구"
        },
        "Crime Occurrence (Cases)": {
            "value": "1,857,276",
            "category_en": "Crime & Safety",
            "category_kr": "범죄와 안전"
        },
        "Registered Foreigners (Person)": {
            "value": "985,923",
            "category_en": "Population",
            "category_kr": "인구"
        },
        "GDP (Hund.M U$)": {
            "value": "14,345.9",
            "category_en": "Economy",
            "category_kr": "경제"
        },
        "mortality rate (per 100 thousand person)": {
            "value": "266,257",
            "category_en": "Health",
            "category_kr": "보건"
        },
        "Unemployment rate (%)": {
            "value": "3.1",
            "category_en": "Labor",
            "category_kr": "노동"
        },
        "Liabilities (10 thousand won)": {
            "value": "5,857.80",
            "category_en": "Income, Consumption and Assets",
            "category_kr": "소득, 소비, 자산"
        },
        "Area of the land (㎡)": {
            "value": "100,266,245,030.0",
            "category_en": "Land Use",
            "category_kr": "국토이용"
        }
    },
    "2014": {
        "Resident Population (Person)": {
            "value": "51,327,916",
            "category_en": "Population",
            "category_kr": "인구"
        },
        "Births (Person)": {
            "value": "435,435",
            "category_en": "Population",
            "category_kr": "인구"
        },
        "Deaths (Person)": {
            "value": "267,692",
            "category_en": "Population",
            "category_kr": "인구"
        },
        "Resident Households (households)": {
            "value": "20,724,094",
            "category_en": "Population",
            "category_kr": "인구"
        },
        "Crime Occurrence (Cases)": {
            "value": "1,778,966",
            "category_en": "Crime & Safety",
            "category_kr": "범죄와 안전"
        },
        "Registered Foreigners (Person)": {
            "value": "1,091,531",
            "category_en": "Population",
            "category_kr": "인구"
        },
        "GDP (Hund.M U$)": {
            "value": "15,556.9",
            "category_en": "Economy",
            "category_kr": "경제"
        },
        "mortality rate (per 100 thousand person)": {
            "value": "267,692",
            "category_en": "Health",
            "category_kr": "보건"
        },
        "Unemployment rate (%)": {
            "value": "3.5",
            "category_en": "Labor",
            "category_kr": "노동"
        },
        "Liabilities (10 thousand won)": {
            "value": "6,050.97",
            "category_en": "Income, Consumption and Assets",
            "category_kr": "소득, 소비, 자산"
        },
        "Area of the land (㎡)": {
            "value": "100,283,945,001.3",
            "category_en": "Land Use",
            "category_kr": "국토이용"
        }
    },
    "2015": {
        "Resident Population (Person)": {
            "value": "51,529,338",
            "category_en": "Population",
            "category_kr": "인구"
        },
        "Births (Person)": {
            "value": "438,420",
            "category_en": "Population",
            "category_kr": "인구"
        },
        "Deaths (Person)": {
            "value": "275,895",
            "category_en": "Population",
            "category_kr": "인구"
        },
        "Household (households)": {
            "value": "19,560,603",
            "category_en": "Population",
            "category_kr": "인구"
        },
        "Resident Households (households)": {
            "value": "21,011,152",
            "category_en": "Population",
            "category_kr": "인구"
        },
        "Crime Occurrence (Cases)": {
            "value": "1,861,657",
            "category_en": "Crime & Safety",
            "category_kr": "범죄와 안전"
        },
        "Registered Foreigners (Person)": {
            "value": "1,143,087",
            "category_en": "Population",
            "category_kr": "인구"
        },
        "GDP (Hund.M U$)": {
            "value": "15,384.8",
            "category_en": "Economy",
            "category_kr": "경제"
        },
        "mortality rate (per 100 thousand person)": {
            "value": "275,895",
            "category_en": "Health",
            "category_kr": "보건"
        },
        "Unemployment rate (%)": {
            "value": "3.6",
            "category_en": "Labor",
            "category_kr": "노동"
        },
        "Liabilities (10 thousand won)": {
            "value": "6,256.15",
            "category_en": "Income, Consumption and Assets",
            "category_kr": "소득, 소비, 자산"
        },
        "Area of the land (㎡)": {
            "value": "100,295,350,806.0",
            "category_en": "Land Use",
            "category_kr": "국토이용"
        }
    },
    "2016": {
        "Resident Population (Person)": {
            "value": "51,696,216",
            "category_en": "Population",
            "category_kr": "인구"
        },
        "Births (Person)": {
            "value": "406,243",
            "category_en": "Population",
            "category_kr": "인구"
        },
        "Deaths (Person)": {
            "value": "280,827",
            "category_en": "Population",
            "category_kr": "인구"
        },
        "Household (households)": {
            "value": "19,837,665",
            "category_en": "Population",
            "category_kr": "인구"
        },
        "Resident Households (households)": {
            "value": "21,294,009",
            "category_en": "Population",
            "category_kr": "인구"
        },
        "Crime Occurrence (Cases)": {
            "value": "1,849,450",
            "category_en": "Crime & Safety",
            "category_kr": "범죄와 안전"
        },
        "Registered Foreigners (Person)": {
            "value": "1,161,677",
            "category_en": "Population",
            "category_kr": "인구"
        },
        "GDP (Hund.M U$)": {
            "value": "15,795.1",
            "category_en": "Economy",
            "category_kr": "경제"
        },
        "mortality rate (per 100 thousand person)": {
            "value": "280,827",
            "category_en": "Health",
            "category_kr": "보건"
        },
        "Unemployment rate (%)": {
            "value": "3.7",
            "category_en": "Labor",
            "category_kr": "노동"
        },
        "Liabilities (10 thousand won)": {
            "value": "6,718.89",
            "category_en": "Income, Consumption and Assets",
            "category_kr": "소득, 소비, 자산"
        },
        "Area of the land (㎡)": {
            "value": "100,339,486,194.1",
            "category_en": "Land Use",
            "category_kr": "국토이용"
        }
    },
    "2017": {
        "Resident Population (Person)": {
            "value": "51,778,544",
            "category_en": "Population",
            "category_kr": "인구"
        },
        "Births (Person)": {
            "value": "357,771",
            "category_en": "Population",
            "category_kr": "인구"
        },
        "Deaths (Person)": {
            "value": "285,534",
            "category_en": "Population",
            "category_kr": "인구"
        },
        "Household (households)": {
            "value": "20,167,922",
            "category_en": "Population",
            "category_kr": "인구"
        },
        "Resident Households (households)": {
            "value": "21,632,851",
            "category_en": "Population",
            "category_kr": "인구"
        },
        "Crime Occurrence (Cases)": {
            "value": "1,662,341",
            "category_en": "Crime & Safety",
            "category_kr": "범죄와 안전"
        },
        "Registered Foreigners (Person)": {
            "value": "1,171,762",
            "category_en": "Population",
            "category_kr": "인구"
        },
        "GDP (Hund.M U$)": {
            "value": "17,104.4",
            "category_en": "Economy",
            "category_kr": "경제"
        },
        "mortality rate (per 100 thousand person)": {
            "value": "285,534",
            "category_en": "Health",
            "category_kr": "보건"
        },
        "Unemployment rate (%)": {
            "value": "3.7",
            "category_en": "Labor",
            "category_kr": "노동"
        },
        "Liabilities (10 thousand won)": {
            "value": "7,099.09",
            "category_en": "Income, Consumption and Assets",
            "category_kr": "소득, 소비, 자산"
        },
        "Area of the land (㎡)": {
            "value": "100,363,715,033.7",
            "category_en": "Land Use",
            "category_kr": "국토이용"
        }
    },
    "2018": {
        "Resident Population (Person)": {
            "value": "51,826,059",
            "category_en": "Population",
            "category_kr": "인구"
        },
        "Births (Person)": {
            "value": "326,822",
            "category_en": "Population",
            "category_kr": "인구"
        },
        "Deaths (Person)": {
            "value": "298,820",
            "category_en": "Population",
            "category_kr": "인구"
        },
        "Household (households)": {
            "value": "20,499,543",
            "category_en": "Population",
            "category_kr": "인구"
        },
        "Resident Households (households)": {
            "value": "22,042,947",
            "category_en": "Population",
            "category_kr": "인구"
        },
        "Crime Occurrence (Cases)": {
            "value": "1,580,751",
            "category_en": "Crime & Safety",
            "category_kr": "범죄와 안전"
        },
        "Registered Foreigners (Person)": {
            "value": "1,246,626",
            "category_en": "Population",
            "category_kr": "인구"
        },
        "GDP (Hund.M U$)": {
            "value": "18,240.2",
            "category_en": "Economy",
            "category_kr": "경제"
        },
        "mortality rate (per 100 thousand person)": {
            "value": "298,820",
            "category_en": "Health",
            "category_kr": "보건"
        },
        "Unemployment rate (%)": {
            "value": "3.8",
            "category_en": "Labor",
            "category_kr": "노동"
        },
        "Liabilities (10 thousand won)": {
            "value": "7,668.18",
            "category_en": "Income, Consumption and Assets",
            "category_kr": "소득, 소비, 자산"
        },
        "Area of the land (㎡)": {
            "value": "100,377,668,317.6",
            "category_en": "Land Use",
            "category_kr": "국토이용"
        }
    },
    "2019": {
        "Resident Population (Person)": {
            "value": "51,849,861",
            "category_en": "Population",
            "category_kr": "인구"
        },
        "Births (Person)": {
            "value": "302,676",
            "category_en": "Population",
            "category_kr": "인구"
        },
        "Deaths (Person)": {
            "value": "295,110",
            "category_en": "Population",
            "category_kr": "인구"
        },
        "Household (households)": {
            "value": "20,891,348",
            "category_en": "Population",
            "category_kr": "인구"
        },
        "Resident Households (households)": {
            "value": "22,481,466",
            "category_en": "Population",
            "category_kr": "인구"
        },
        "Crime Occurrence (Cases)": {
            "value": "1,611,906",
            "category_en": "Crime & Safety",
            "category_kr": "범죄와 안전"
        },
        "Registered Foreigners (Person)": {
            "value": "1,271,807",
            "category_en": "Population",
            "category_kr": "인구"
        },
        "GDP (Hund.M U$)": {
            "value": "17,506.1",
            "category_en": "Economy",
            "category_kr": "경제"
        },
        "mortality rate (per 100 thousand person)": {
            "value": "295,110",
            "category_en": "Health",
            "category_kr": "보건"
        },
        "Unemployment rate (%)": {
            "value": "3.8",
            "category_en": "Labor",
            "category_kr": "노동"
        },
        "Liabilities (10 thousand won)": {
            "value": "7,910.17",
            "category_en": "Income, Consumption and Assets",
            "category_kr": "소득, 소비, 자산"
        },
        "Area of the land (㎡)": {
            "value": "100,401,284,999.9",
            "category_en": "Land Use",
            "category_kr": "국토이용"
        }
    },
    "2020": {
        "Resident Population (Person)": {
            "value": "51,829,023",
            "category_en": "Population",
            "category_kr": "인구"
        },
        "Births (Person)": {
            "value": "272,337",
            "category_en": "Population",
            "category_kr": "인구"
        },
        "Deaths (Person)": {
            "value": "304,948",
            "category_en": "Population",
            "category_kr": "인구"
        },
        "Household (households)": {
            "value": "21,484,785",
            "category_en": "Population",
            "category_kr": "인구"
        },
        "Resident Households (households)": {
            "value": "23,093,108",
            "category_en": "Population",
            "category_kr": "인구"
        },
        "Crime Occurrence (Cases)": {
            "value": "1,587,866",
            "category_en": "Crime & Safety",
            "category_kr": "범죄와 안전"
        },
        "Registered Foreigners (Person)": {
            "value": "1,145,540",
            "category_en": "Population",
            "category_kr": "인구"
        },
        "GDP (Hund.M U$)": {
            "value": "17,443.9",
            "category_en": "Economy",
            "category_kr": "경제"
        },
        "mortality rate (per 100 thousand person)": {
            "value": "304,948",
            "category_en": "Health",
            "category_kr": "보건"
        },
        "Unemployment rate (%)": {
            "value": "4.0",
            "category_en": "Labor",
            "category_kr": "노동"
        },
        "Liabilities (10 thousand won)": {
            "value": "8,256.19",
            "category_en": "Income, Consumption and Assets",
            "category_kr": "소득, 소비, 자산"
        },
        "Area of the land (㎡)": {
            "value": "100,412,598,711.4",
            "category_en": "Land Use",
            "category_kr": "국토이용"
        }
    },
    "2021": {
        "Resident Population (Person)": {
            "value": "51,638,809",
            "category_en": "Population",
            "category_kr": "인구"
        },
        "Births (Person)": {
            "value": "260,562",
            "category_en": "Population",
            "category_kr": "인구"
        },
        "Deaths (Person)": {
            "value": "317,680",
            "category_en": "Population",
            "category_kr": "인구"
        },
        "Household (households)": {
            "value": "22,022,753",
            "category_en": "Population",
            "category_kr": "인구"
        },
        "Resident Households (households)": {
            "value": "23,472,895",
            "category_en": "Population",
            "category_kr": "인구"
        },
        "Crime Occurrence (Cases)": {
            "value": "1,429,826",
            "category_en": "Crime & Safety",
            "category_kr": "범죄와 안전"
        },
        "Registered Foreigners (Person)": {
            "value": "1,093,891",
            "category_en": "Population",
            "category_kr": "인구"
        },
        "GDP (Hund.M U$)": {
            "value": "19,415.2",
            "category_en": "Economy",
            "category_kr": "경제"
        },
        "mortality rate (per 100 thousand person)": {
            "value": "317,680",
            "category_en": "Health",
            "category_kr": "보건"
        },
        "Unemployment rate (%)": {
            "value": "3.7",
            "category_en": "Labor",
            "category_kr": "노동"
        },
        "Liabilities (10 thousand won)": {
            "value": "8,801.37",
            "category_en": "Income, Consumption and Assets",
            "category_kr": "소득, 소비, 자산"
        },
        "Area of the land (㎡)": {
            "value": "100,431,849,363.5",
            "category_en": "Land Use",
            "category_kr": "국토이용"
        }
    },
    "2022": {
        "Resident Population (Person)": {
            "value": "51,439,038",
            "category_en": "Population",
            "category_kr": "인구"
        },
        "Births (Person)": {
            "value": "249,186",
            "category_en": "Population",
            "category_kr": "인구"
        },
        "Deaths (Person)": {
            "value": "372,939",
            "category_en": "Population",
            "category_kr": "인구"
        },
        "Household (households)": {
            "value": "22,383,187",
            "category_en": "Population",
            "category_kr": "인구"
        },
        "Resident Households (households)": {
            "value": "23,705,814",
            "category_en": "Population",
            "category_kr": "인구"
        },
        "Crime Occurrence (Cases)": {
            "value": "1,482,433",
            "category_en": "Crime & Safety",
            "category_kr": "범죄와 안전"
        },
        "Registered Foreigners (Person)": {
            "value": "1,189,585",
            "category_en": "Population",
            "category_kr": "인구"
        },
        "GDP (Hund.M U$)": {
            "value": "17,986.6",
            "category_en": "Economy",
            "category_kr": "경제"
        },
        "mortality rate (per 100 thousand person)": {
            "value": "372,939",
            "category_en": "Health",
            "category_kr": "보건"
        },
        "Unemployment rate (%)": {
            "value": "2.9",
            "category_en": "Labor",
            "category_kr": "노동"
        },
        "Liabilities (10 thousand won)": {
            "value": "9,169.61",
            "category_en": "Income, Consumption and Assets",
            "category_kr": "소득, 소비, 자산"
        },
        "Area of the land (㎡)": {
            "value": "100,443,553,474.5",
            "category_en": "Land Use",
            "category_kr": "국토이용"
        }
    },
    "2023": {
        "Resident Population (Person)": {
            "value": "51,325,329",
            "category_en": "Population",
            "category_kr": "인구"
        },
        "Births (Person)": {
            "value": "230,028",
            "category_en": "Population",
            "category_kr": "인구"
        },
        "Deaths (Person)": {
            "value": "352,511",
            "category_en": "Population",
            "category_kr": "인구"
        },
        "Household (households)": {
            "value": "22,728,163",
            "category_en": "Population",
            "category_kr": "인구"
        },
        "Resident Households (households)": {
            "value": "23,914,851",
            "category_en": "Population",
            "category_kr": "인구"
        },
        "Registered Foreigners (Person)": {
            "value": "1,348,626",
            "category_en": "Population",
            "category_kr": "인구"
        },
        "GDP (Hund.M U$)": {
            "value": "18,394.1",
            "category_en": "Economy",
            "category_kr": "경제"
        },
        "mortality rate (per 100 thousand person)": {
            "value": "352,511",
            "category_en": "Health",
            "category_kr": "보건"
        },
        "Unemployment rate (%)": {
            "value": "2.7",
            "category_en": "Labor",
            "category_kr": "노동"
        },
        "Liabilities (10 thousand won)": {
            "value": "9,186.40",
            "category_en": "Income, Consumption and Assets",
            "category_kr": "소득, 소비, 자산"
        },
        "Area of the land (㎡)": {
            "value": "100,449,356,102.0",
            "category_en": "Land Use",
            "category_kr": "국토이용"
        }
    },
    "2024": {
        "Resident Population (Person)": {
            "value": "51,217,221",
            "category_en": "Population",
            "category_kr": "인구"
        },
        "Resident Households (households)": {
            "value": "24,118,928",
            "category_en": "Population",
            "category_kr": "인구"
        },
        "Unemployment rate (%)": {
            "value": "2.8",
            "category_en": "Labor",
            "category_kr": "노동"
        },
        "Liabilities (10 thousand won)": {
            "value": "9,128.25",
            "category_en": "Income, Consumption and Assets",
            "category_kr": "소득, 소비, 자산"
        }
    }
}